README.txt
setup.cfg
setup.py
collective/__init__.py
collective.calendarwidget.egg-info/PKG-INFO
collective.calendarwidget.egg-info/SOURCES.txt
collective.calendarwidget.egg-info/dependency_links.txt
collective.calendarwidget.egg-info/entry_points.txt
collective.calendarwidget.egg-info/namespace_packages.txt
collective.calendarwidget.egg-info/not-zip-safe
collective.calendarwidget.egg-info/requires.txt
collective.calendarwidget.egg-info/top_level.txt
collective/calendarwidget/__init__.py
collective/calendarwidget/configure.zcml
collective/calendarwidget/header.txt
collective/calendarwidget/widget.py
collective/calendarwidget/browser/__init__.py
collective/calendarwidget/browser/calendarwidget.js
collective/calendarwidget/browser/configure.zcml
collective/calendarwidget/profiles/default/cssregistry.xml
collective/calendarwidget/profiles/default/jsregistry.xml
collective/calendarwidget/profiles/default/metadata.xml
collective/calendarwidget/profiles/default/skins.xml
collective/calendarwidget/skins/collective_calendarwidget/collective_calendarwidget.pt
docs/HISTORY.txt