Metadata-Version: 1.0
Name: collective.calendarwidget
Version: 0.2.5
Summary: A new calendar widget for Archetypes (used for vs.event)
Home-page: http://pypi.python.org/pypi/collective.calendarwidget
Author: Andreas Jung & others
Author-email: info@zopyx.com
License: ZPL
Platform: UNKNOWN
Classifier: Programming Language :: Python
Classifier: Topic :: Software Development :: Libraries :: Python Modules
